AUTHORS.rst
CHANGELOG.rst
LICENSE
MANIFEST.in
README.rst
setup.py
panya_paste/__init__.py
panya_paste/templates.py
panya_paste.egg-info/PKG-INFO
panya_paste.egg-info/SOURCES.txt
panya_paste.egg-info/dependency_links.txt
panya_paste.egg-info/entry_points.txt
panya_paste.egg-info/not-zip-safe
panya_paste.egg-info/requires.txt
panya_paste.egg-info/top_level.txt
panya_paste/config/chart_urlconf_additions.py
panya_paste/config/ckeditor_urlconf_additions.py
panya_paste/config/competition_urlconf_additions.py
panya_paste/config/contact_urlconf_additions.py
panya_paste/config/event_urlconf_additions.py
panya_paste/config/gallery_urlconf_additions.py
panya_paste/config/googlesearch_urlconf_additions.py
panya_paste/config/likes_urlconf_additions.py
panya_paste/config/music_urlconf_additions.py
panya_paste/config/panya_urlconf_additions.py
panya_paste/config/profile_model_additions.py
panya_paste/config/richcomments_urlconf_additions.py
panya_paste/config/show_urlconf_additions.py
panya_paste/templates/panya_project/bootstrap.py
panya_paste/templates/panya_project/buildout.cfg_tmpl
panya_paste/templates/panya_project/buildout_templates/fcgi.in
panya_paste/templates/panya_project/buildout_templates/nginx.conf.in
panya_paste/templates/panya_project/log/nginx/+hostname+/access.log
panya_paste/templates/panya_project/log/nginx/+hostname+/error.log
panya_paste/templates/panya_project/log/nginx/+hostname_staging+/access.log
panya_paste/templates/panya_project/log/nginx/+hostname_staging+/error.log
panya_paste/templates/panya_project/media/uploads/.placeholder
panya_paste/templates/panya_project/src/+project+/MANIFEST.in_tmpl
panya_paste/templates/panya_project/src/+project+/README.rst
panya_paste/templates/panya_project/src/+project+/setup.py_tmpl
panya_paste/templates/panya_project/src/+project+/+project+/__init__.py
panya_paste/templates/panya_project/src/+project+/+project+/gizmos.py
panya_paste/templates/panya_project/src/+project+/+project+/models.py_tmpl
panya_paste/templates/panya_project/src/+project+/+project+/settings.py_tmpl
panya_paste/templates/panya_project/src/+project+/+project+/settings_staging.py_tmpl
panya_paste/templates/panya_project/src/+project+/+project+/urls.py_tmpl
