Metadata-Version: 1.0
Name: panya-paste
Version: 0.1.0
Summary: Python Paste templates creating Panya buildout environments.
Home-page: http://github.com/praekelt/panya-paste
Author: Praekelt Foundation
Author-email: dev@praekelt.com
License: BSD
Platform: UNKNOWN
Classifier: Programming Language :: Python
Classifier: License :: OSI Approved :: BSD License
Classifier: Development Status :: 4 - Beta
Classifier: Operating System :: OS Independent
Classifier: Framework :: Paste
Classifier: Intended Audience :: Developers
Classifier: Topic :: Internet :: WWW/HTTP :: Dynamic Content
